gorequests/__init__.py
gorequests/exceptions.py
gorequests/libgorequests.dll
gorequests-2.0.0.dist-info/licenses/LICENSE
gorequests-2.0.0.dist-info/METADATA
gorequests-2.0.0.dist-info/WHEEL
gorequests-2.0.0.dist-info/top_level.txt
gorequests-2.0.0.dist-info/RECORD
