Metadata-Version: 2.4
Name: gorequests
Version: 2.0.0
Summary: High-performance HTTP client library powered by Go FastHTTP
Home-page: https://github.com/coffeecms/gorequests
Author: GoRequests Team
Author-email: GoRequests Team <team@gorequests.io>
Maintainer-email: GoRequests Team <team@gorequests.io>
License: MIT
Project-URL: Homepage, https://github.com/coffeecms/gorequests
Project-URL: Documentation, https://gorequests.readthedocs.io
Project-URL: Repository, https://github.com/coffeecms/gorequests
Project-URL: Bug Tracker, https://github.com/coffeecms/gorequests/issues
Project-URL: Changelog, https://github.com/coffeecms/gorequests/blob/main/CHANGELOG.md
Keywords: http,requests,client,fasthttp,go,performance,async,web,api,networking,fast,gorequests
Classifier: Development Status :: 5 - Production/Stable
Classifier: Intended Audience :: Developers
Classifier: License :: OSI Approved :: MIT License
Classifier: Operating System :: OS Independent
Classifier: Programming Language :: Python :: 3
Classifier: Programming Language :: Python :: 3.7
Classifier: Programming Language :: Python :: 3.8
Classifier: Programming Language :: Python :: 3.9
Classifier: Programming Language :: Python :: 3.10
Classifier: Programming Language :: Python :: 3.11
Classifier: Programming Language :: Python :: 3.12
Classifier: Topic :: Internet :: WWW/HTTP
Classifier: Topic :: Software Development :: Libraries :: Python Modules
Classifier: Topic :: System :: Networking
Requires-Python: >=3.7
License-File: LICENSE
Provides-Extra: dev
Requires-Dist: pytest>=6.0; extra == "dev"
Requires-Dist: pytest-cov>=2.0; extra == "dev"
Requires-Dist: black>=21.0; extra == "dev"
Requires-Dist: flake8>=3.8; extra == "dev"
Requires-Dist: mypy>=0.900; extra == "dev"
Requires-Dist: requests>=2.25.0; extra == "dev"
Provides-Extra: test
Requires-Dist: pytest>=6.0; extra == "test"
Requires-Dist: pytest-cov>=2.0; extra == "test"
Requires-Dist: requests>=2.25.0; extra == "test"
Dynamic: author
Dynamic: home-page
Dynamic: license-file
Dynamic: requires-python
